setup.cfg
setup.py
copyfile/__init__.py
copyfile/copyfile.py
copyfile.egg-info/PKG-INFO
copyfile.egg-info/SOURCES.txt
copyfile.egg-info/dependency_links.txt
copyfile.egg-info/not-zip-safe
copyfile.egg-info/top_level.txt