Metadata-Version: 1.0
Name: copyfile
Version: 0.1
Summary: copies a file to a location which may not exist
Home-page: http://github.com/riordan/py-copyfile
Author: David Riordan
Author-email: dr@daveriordan.com
License: Apache-2.0
Platform: UNKNOWN
